napari_flowreg/__init__.py
napari_flowreg/_version.py
napari_flowreg/flow_visualization_widget.py
napari_flowreg/flowreg_widget.py
napari_flowreg/motion_analysis_widget.py
napari_flowreg/napari.yaml
napari_flowreg-0.1.0a3.dist-info/METADATA
napari_flowreg-0.1.0a3.dist-info/WHEEL
napari_flowreg-0.1.0a3.dist-info/entry_points.txt
napari_flowreg-0.1.0a3.dist-info/top_level.txt
napari_flowreg-0.1.0a3.dist-info/RECORD
