Metadata-Version: 2.4
Name: napari-flowreg
Version: 0.1.0a3
Summary: napari plugin for Flow-Registration motion correction
Author-email: Philipp Flotho <Philipp.Flotho@uni-saarland.de>
License: CC BY-NC-SA 4.0
Project-URL: Homepage, https://github.com/FlowRegSuite/napari-flowreg
Project-URL: Source, https://github.com/FlowRegSuite/napari-flowreg
Project-URL: Tracker, https://github.com/FlowRegSuite/napari-flowreg/issues
Project-URL: Documentation, https://flowregsuite.github.io/napari-flowreg/
Classifier: Development Status :: 3 - Alpha
Classifier: Framework :: napari
Classifier: Programming Language :: Python :: 3
Classifier: Programming Language :: Python :: 3.10
Classifier: Programming Language :: Python :: 3.11
Classifier: Programming Language :: Python :: 3.12
Classifier: Programming Language :: Python :: 3.13
Classifier: License :: OSI Approved :: BSD License
Classifier: Operating System :: OS Independent
Classifier: Topic :: Scientific/Engineering :: Image Processing
Requires-Python: >=3.10
Requires-Dist: pyflowreg[vis]>=0.1.0a4
Requires-Dist: qtpy
Requires-Dist: numpy
Requires-Dist: scipy>=1.10.0
Requires-Dist: matplotlib>=3.5.0
Provides-Extra: testing
Requires-Dist: pytest>=7.0; extra == "testing"
Requires-Dist: pytest-cov>=4.0; extra == "testing"
Requires-Dist: pytest-qt; extra == "testing"
Requires-Dist: h5py; extra == "testing"
Requires-Dist: tifffile; extra == "testing"
Requires-Dist: napari[pyqt6]; extra == "testing"
Provides-Extra: dev
Requires-Dist: napari[pyqt5]>=0.4.18; extra == "dev"
Requires-Dist: pre-commit; extra == "dev"
Requires-Dist: black; extra == "dev"
Requires-Dist: ruff; extra == "dev"
